[
    {
        "id": 1,
        "title": "Aracne",
        "url": "https://www.gamtorino.it/it/le-collezioni/catalogo-delle-opere-online-gam/aracne"
    },
    {
        "id": 2,
        "title": "Marina",
        "url": "https://www.gamtorino.it/en/node/39384"
    },
    {
        "id": 3,
        "title": "Asfissia! (parte sinistra)",
        "url": "https://www.gamtorino.it/en/node/39175"
    },
    {
        "id": 4,
        "title": "La Sirena (Sirena) (Abisso verde)",
        "url": "https://www.gamtorino.it/it/le-collezioni/catalogo-delle-opere-online-gam/la-sirena-sirena-abisso-verde"
    },
    {
        "id": 5,
        "title": "Mercato Vecchio di Firenze",
        "url": "https://www.gamtorino.it/it/le-collezioni/catalogo-delle-opere-online-gam/mercato-vecchio-di-firenze"
    },
    {
        "id": 6,
        "title": "Aprile",
        "url": "https://www.gamtorino.it/en/node/35215"
    },
    {
        "id": 7,
        "title": "Daphne (Daphne a Pavarolo)",
        "url": "https://www.gamtorino.it/en/node/35323"
    },
    {
        "id": 8,
        "title": "La ragazza rossa (Testa di donna dai capelli rossi)",
        "url": "https://www.gamtorino.it/it/le-collezioni/catalogo-delle-opere-online-gam/la-ragazza-rossa-testa-di-donna-dai-capelli-rossi"
    },
    {
        "id": 9,
        "title": "Estate (L'amaca)",
        "url": "https://www.gamtorino.it/en/node/35380"
    },
    {
        "id": 10,
        "title": "Gotine rosse",
        "url": "https://www.gamtorino.it/en/node/35221"
    },
    {
        "id": 11,
        "title": "Lo specchio della vita (E ciò che l'una fa, e le altre fanno)",
        "url": "https://www.gamtorino.it/en/node/35307"
    },
    {
        "id": 12,
        "title": "Autoritratto in forma di gufo",
        "url": "https://www.gamtorino.it/en/node/35381" 
    }
]
